{
	"layers": [
		{
			"id": "G6I",
			"wrrID": "DelawareWRR_RP_5181",
			"title": "Riparian Preservation",
			"category": "WRR Suitability Analyses"
		},
		{
			"id": "JW2",
			"wrrID": "DelawareWRR_RR_2326",
			"title": "Riparian Restoration",
			"category": "WRR Suitability Analyses"
		},
		{
			"id": "Wus",
			"wrrID": "DelawareWRR_HP_4563",
			"title": "Stormwater Natural Infrastructure Preservation",
			"category": "WRR Suitability Analyses"
		},
		{
			"id": "J1K",
			"wrrID": "DelawareWRR_HR_6118",
			"title": "Stormwater Compromised Infrastructure Restoration",
			"category": "WRR Suitability Analyses"
		},
		{
			"id": "upC",
			"wrrID": "DelawareWRR_UP_4462",
			"title": "Upland Preservation",
			"category": "WRR Suitability Analyses"
		},
		{
			"id": "5uI",
			"wrrID": "DelawareWRR_UR_4569",
			"title": "Upland Restoration",
			"category": "WRR Suitability Analyses"
		},
		{
			"id": "EVA",
			"wrrID": "DelawareWRR_WP_8043",
			"title": "Wetland Preservation",
			"category": "WRR Suitability Analyses"
		},
		{
			"id": "Shm",
			"wrrID": "DelawareWRR_WR_3750",
			"title": "Wetland Restoration",
			"category": "WRR Suitability Analyses"
		},
		{
			"id": "h5O",
			"wrrID": "ORM_4776",
			"title": "ORM - Updated 8/10/22",
			"category": "Permits"
		},
		{
			"id": "49E",
			"wrrID": "RIBITS_5451",
			"title": "RIBITS - Banks & Service Areas",
			"category": "Permits"
		},
		{
			"id": "wSw",
			"wrrID": "NPDES_NP21_912",
			"title": "Facilities that Discharge to Water",
			"category": "Permits"
		},
		{
			"id": "pZq",
			"wrrID": "survey123_f428e20cada347319bfc88cd00a82a98_fieldworker_9697",
			"title": "Site Visit Location",
			"category": "Site Visit Locations"
		},
		{
			"id": "u72",
			"wrrID": "DE_Wetlands_7283",
			"title": "Delaware Wetlands - 1992",
			"category": "Water Resources"
		},
		{
			"id": "4fQ",
			"wrrID": "DE_Wetlands_7399",
			"title": "Delaware Wetlands - 2007",
			"category": "Water Resources"
		},
		{
			"id": "akO",
			"wrrID": "DE_Wetlands_1277",
			"title": "Delaware Wetlands - 2017",
			"category": "Water Resources"
		},
		{
			"id": "f5n",
			"wrrID": "DE_Wetlands_3700",
			"title": "2007 Head of Tide Wetlands",
			"category": "Water Resources"
		},
		{
			"id": "sUz",
			"wrrID": "DE_Wetlands_8485",
			"title": "2017 High Marsh",
			"category": "Water Resources"
		},
		{
			"id": "JnA",
			"wrrID": "DE_Wetlands_8599",
			"title": "2017 Low Marsh",
			"category": "Water Resources"
		},
		{
			"id": "o8F",
			"wrrID": "DE_Fish_Ladders_912",
			"title": "DE Fish Ladders",
			"category": "Water Resources"
		},
		{
			"id": "iX3",
			"wrrID": "Wetlands_128",
			"title": "USFWS NWI",
			"category": "Water Resources"
		},
		{
			"id": "mIP",
			"wrrID": "wbd_629",
			"title": "USGS Watershed Boundaries",
			"category": "Water Resources"
		},
		{
			"id": "6Vp",
			"wrrID": "DE_Watersheds_9568",
			"title": "Old DNREC Watersheds",
			"category": "Water Resources"
		},
		{
			"id": "6pd",
			"wrrID": "DE_TaxDitch_9232",
			"title": "Tax Ditch",
			"category": "Water Resources"
		},
		{
			"id": "aBG",
			"wrrID": "DE_Water_3521",
			"title": "Water Features",
			"category": "Water Resources"
		},
		{
			"id": "jiV",
			"wrrID": "DGS_WaterTableElevation_2899",
			"title": "Water Table Elevation (meters)",
			"category": "Water Resources"
		},
		{
			"id": "fo0",
			"wrrID": "EDW_WildScenicRiverSegments_01_4047",
			"title": "Wild and Scenic Rivers",
			"category": "Water Resources"
		},
		{
			"id": "7Cy",
			"wrrID": "NPS_Watershed_Plans_7735",
			"title": "319 Watersheds",
			"category": "Water Resources"
		},
		{
			"id": "olC",
			"wrrID": "DE_Watersheds_8909",
			"title": "HUC 2",
			"category": "USGS HUC Watersheds"
		},
		{
			"id": "DqD",
			"wrrID": "DE_Watersheds_9331",
			"title": "HUC 4",
			"category": "USGS HUC Watersheds"
		},
		{
			"id": "zHx",
			"wrrID": "DE_Watersheds_5978",
			"title": "HUC 6",
			"category": "USGS HUC Watersheds"
		},
		{
			"id": "8mU",
			"wrrID": "DE_Watersheds_6571",
			"title": "HUC 8",
			"category": "USGS HUC Watersheds"
		},
		{
			"id": "qFh",
			"wrrID": "DE_Watersheds_8508",
			"title": "HUC 10",
			"category": "USGS HUC Watersheds"
		},
		{
			"id": "Rdx",
			"wrrID": "DE_Watersheds_1957",
			"title": "HUC 12",
			"category": "USGS HUC Watersheds"
		},
		{
			"id": "96B",
			"wrrID": "DE_WellHeadProtectionAreas_4672",
			"title": "Well Head Protection Areas",
			"category": "Water Protection"
		},
		{
			"id": "UNW",
			"wrrID": "DGS_GroundwaterRechargePotential_3759",
			"title": "Groundwater Recharge Areas",
			"category": "Water Protection"
		},
		{
			"id": "EZS",
			"wrrID": "DE_RR_Feasibility_7562",
			"title": "Runoff Reduction Feasibility",
			"category": "Water Protection"
		},
		{
			"id": "Sp2",
			"wrrID": "NHDPlus_HR_1500",
			"title": "NHD Plus Sink",
			"category": "National Hydrography Dataset"
		},
		{
			"id": "v4S",
			"wrrID": "NHDPlus_HR_1802",
			"title": "NHD Point",
			"category": "National Hydrography Dataset"
		},
		{
			"id": "kN6",
			"wrrID": "NHDPlus_HR_4719",
			"title": "Network NHD Flowline",
			"category": "National Hydrography Dataset"
		},
		{
			"id": "Q6I",
			"wrrID": "NHDPlus_HR_2432",
			"title": "Non-Network NHD Flowline",
			"category": "National Hydrography Dataset"
		},
		{
			"id": "AAa",
			"wrrID": "NHDPlus_HR_5109",
			"title": "Flow Direction",
			"category": "National Hydrography Dataset"
		},
		{
			"id": "5AM",
			"wrrID": "NHDPlus_HR_1172",
			"title": "NHD Plus Wall",
			"category": "National Hydrography Dataset"
		},
		{
			"id": "E4E",
			"wrrID": "NHDPlus_HR_4922",
			"title": "NHD Plus Burn Line Event",
			"category": "National Hydrography Dataset"
		},
		{
			"id": "k7Y",
			"wrrID": "NHDPlus_HR_1105",
			"title": "NHD Line",
			"category": "National Hydrography Dataset"
		},
		{
			"id": "uWL",
			"wrrID": "NHDPlus_HR_2934",
			"title": "NHD Area",
			"category": "National Hydrography Dataset"
		},
		{
			"id": "c4j",
			"wrrID": "NHDPlus_HR_7395",
			"title": "NHD Waterbody",
			"category": "National Hydrography Dataset"
		},
		{
			"id": "TDL",
			"wrrID": "NHDPlus_HR_1431",
			"title": "NHD Plus Catchment",
			"category": "National Hydrography Dataset"
		},
		{
			"id": "TLX",
			"wrrID": "NHDPlus_HR_154",
			"title": "WBD HU12",
			"category": "National Hydrography Dataset"
		},
		{
			"id": "q80",
			"wrrID": "DNREC_Watershed_Grade_7105",
			"title": "All Watersheds",
			"category": "Watershed Wetland Health Assessments"
		},
		{
			"id": "G6r",
			"wrrID": "DNREC_Watersheds_2576",
			"title": "Watershed Points",
			"category": "Watershed Wetland Health Assessments"
		},
		{
			"id": "Io7",
			"wrrID": "Appoquinimink_Watershed_4675",
			"title": "Appoquinimink River",
			"category": "Watershed Wetland Health Assessments"
		},
		{
			"id": "ocm",
			"wrrID": "Brandywine_Watershed_675",
			"title": "Brandywine Creek",
			"category": "Watershed Wetland Health Assessments"
		},
		{
			"id": "nAf",
			"wrrID": "Broadkill_Watershed_9998",
			"title": "Broadkill River",
			"category": "Watershed Wetland Health Assessments"
		},
		{
			"id": "Beu",
			"wrrID": "Christina_Watershed_5665",
			"title": "Christina River",
			"category": "Watershed Wetland Health Assessments"
		},
		{
			"id": "gOB",
			"wrrID": "Chester_Choptank_Watershed_8709",
			"title": "Chester-Choptank Rivers",
			"category": "Watershed Wetland Health Assessments"
		},
		{
			"id": "xqI",
			"wrrID": "Inland_Watershed_4803",
			"title": "Inland Bays",
			"category": "Watershed Wetland Health Assessments"
		},
		{
			"id": "Coz",
			"wrrID": "Leipsic_Watershed_2601",
			"title": "Leipsic River",
			"category": "Watershed Wetland Health Assessments"
		},
		{
			"id": "cgd",
			"wrrID": "Mispillion_Watershed_9172",
			"title": "Mispillion River",
			"category": "Watershed Wetland Health Assessments"
		},
		{
			"id": "Ydp",
			"wrrID": "Murderkill_Watershed_5344",
			"title": "Murderkill River",
			"category": "Watershed Wetland Health Assessments"
		},
		{
			"id": "Bjf",
			"wrrID": "Nanticoke_Watershed_5297",
			"title": "Nanticoke River",
			"category": "Watershed Wetland Health Assessments"
		},
		{
			"id": "Hzj",
			"wrrID": "Red_Lion_Watershed_1009",
			"title": "Red Lion Creek",
			"category": "Watershed Wetland Health Assessments"
		},
		{
			"id": "Wb7",
			"wrrID": "Smyrna_Watershed_2170",
			"title": "Smyrna River",
			"category": "Watershed Wetland Health Assessments"
		},
		{
			"id": "903",
			"wrrID": "StJones_Watershed_7371",
			"title": "St. Jones River",
			"category": "Watershed Wetland Health Assessments"
		},
		{
			"id": "sw7",
			"wrrID": "DE_Contours_2014_2591",
			"title": "Elevation Contours",
			"category": "Elevation"
		},
		{
			"id": "yQ2",
			"wrrID": "DE_Contours_2014_8308",
			"title": "NCC Upper",
			"category": "Elevation"
		},
		{
			"id": "bsf",
			"wrrID": "DE_Contours_2014_3383",
			"title": "NCC Lower",
			"category": "Elevation"
		},
		{
			"id": "Bx4",
			"wrrID": "DE_Contours_2014_6272",
			"title": "Kent Contour",
			"category": "Elevation"
		},
		{
			"id": "Yku",
			"wrrID": "DE_Contours_2014_5511",
			"title": "Sussex Contour",
			"category": "Elevation"
		},
		{
			"id": "KwH",
			"wrrID": "DE_Lidar_DEM_4884",
			"title": "LiDAR",
			"category": "Elevation"
		},
		{
			"id": "8fW",
			"wrrID": "DE_DNREC_DEN_Features_326",
			"title": "FEMA Flood Maps",
			"category": "Flood Risk"
		},
		{
			"id": "zeB",
			"wrrID": "DE_FloodRiskAdaptationMap_2577",
			"title": "Flood Risk Adaptation Map",
			"category": "Flood Risk"
		},
		{
			"id": "E4x",
			"wrrID": "DE_Coastal_Inundation_2017_4188",
			"title": "Mean Higher High Water (MHHW)",
			"category": "Flood Risk"
		},
		{
			"id": "8Kx",
			"wrrID": "DE_Coastal_Inundation_2017_1318",
			"title": "Sea Level Rise - 1 ft",
			"category": "Flood Risk"
		},
		{
			"id": "Ymg",
			"wrrID": "DE_Coastal_Inundation_2017_1931",
			"title": "Sea Level Rise - 2 ft",
			"category": "Flood Risk"
		},
		{
			"id": "hI2",
			"wrrID": "DE_Coastal_Inundation_2017_4799",
			"title": "Sea Level Rise - 3 ft",
			"category": "Flood Risk"
		},
		{
			"id": "DCr",
			"wrrID": "DE_Coastal_Inundation_2017_5421",
			"title": "Sea Level Rise - 4 ft",
			"category": "Flood Risk"
		},
		{
			"id": "rDo",
			"wrrID": "DE_Coastal_Inundation_2017_5124",
			"title": "Sea Level Rise - 5 ft",
			"category": "Flood Risk"
		},
		{
			"id": "M8T",
			"wrrID": "DE_Coastal_Inundation_2017_9514",
			"title": "Sea Level Rise - 6 ft",
			"category": "Flood Risk"
		},
		{
			"id": "EKJ",
			"wrrID": "DE_Coastal_Inundation_2017_9619",
			"title": "Sea Level Rise - 7 ft",
			"category": "Flood Risk"
		},
		{
			"id": "Tqt",
			"wrrID": "DE_HistoricPlaces_4974",
			"title": "Historic Places",
			"category": "Historic Resources"
		},
		{
			"id": "aMH",
			"wrrID": "DE_Assets_2283",
			"title": "Historic Markers",
			"category": "Historic Resources"
		},
		{
			"id": "9MH",
			"wrrID": "DE_Geographic_Names_3106",
			"title": "Historic Cultural",
			"category": "Historic Resources"
		},
		{
			"id": "l5g",
			"wrrID": "NLCD_2016_Land_Cover_L48_897",
			"title": "NLCD 2016 Land Cover",
			"category": "Land Planning"
		},
		{
			"id": "Ek5",
			"wrrID": "NCED_CompleteDB_8572",
			"title": "NCED Conservation Easements",
			"category": "Land Planning"
		},
		{
			"id": "0Fc",
			"wrrID": "DE_Protected_Natural_Resources_3884",
			"title": "Nature Preserves",
			"category": "Land Planning"
		},
		{
			"id": "ZZb",
			"wrrID": "DE_Protected_Natural_Resources_7906",
			"title": "Park Facilities",
			"category": "Land Planning"
		},
		{
			"id": "b3Z",
			"wrrID": "DE_Protected_Natural_Resources_6202",
			"title": "Public Protected Lands",
			"category": "Land Planning"
		},
		{
			"id": "asA",
			"wrrID": "DE_Protected_Natural_Resources_4481",
			"title": "Natural Areas",
			"category": "Land Planning"
		},
		{
			"id": "agZ",
			"wrrID": "DE_LULC_2007_Revised_2623",
			"title": "State Land Cover - 2007 (Revised)",
			"category": "Land Planning"
		},
		{
			"id": "49I",
			"wrrID": "DE_LULC_6916",
			"title": "State Land Cover - 2012",
			"category": "Land Planning"
		},
		{
			"id": "VHK",
			"wrrID": "DE_LULC_4791",
			"title": "State Land Cover - 2017",
			"category": "Land Planning"
		},
		{
			"id": "hTf",
			"wrrID": "DE_Enviro_Justice_7685",
			"title": "Environmental Justice",
			"category": "Land Planning"
		},
		{
			"id": "I5T",
			"wrrID": "DE_AgLandsPreservation_1853",
			"title": "Ag Land Preservation",
			"category": "Land Planning"
		},
		{
			"id": "sXF",
			"wrrID": "DE_AgLandsPreservation_8797",
			"title": "Forest Legacy",
			"category": "Land Planning"
		},
		{
			"id": "kTy",
			"wrrID": "wms_2570",
			"title": "NRCS Soil Data",
			"category": "Ecological & Soil Resources"
		},
		{
			"id": "K9I",
			"wrrID": "DE_Ecological_Network_5738",
			"title": "DE Ecological Network",
			"category": "Ecological & Soil Resources"
		},
		{
			"id": "7oW",
			"wrrID": "ImportantBirdAreas_Point_8677",
			"title": "Important Bird Areas Point",
			"category": "Ecological & Soil Resources"
		},
		{
			"id": "z9R",
			"wrrID": "ImportantBirdAreas_Polygon_3468",
			"title": "Important Bird Areas Polygon",
			"category": "Ecological & Soil Resources"
		},
		{
			"id": "rLu",
			"wrrID": "DE_Roadways_Main_5276",
			"title": "Road Inventory",
			"category": "Transportation"
		},
		{
			"id": "v8m",
			"wrrID": "DE_Multimodal_9167",
			"title": "Aeronautics - DAFB Gate Entrances",
			"category": "Transportation"
		},
		{
			"id": "8i2",
			"wrrID": "DE_Multimodal_7720",
			"title": "Aeronautics - Airports",
			"category": "Transportation"
		},
		{
			"id": "3fX",
			"wrrID": "DE_Multimodal_6118",
			"title": "Aeronautics - Airport Notification Areas",
			"category": "Transportation"
		},
		{
			"id": "s4Q",
			"wrrID": "DE_Multimodal_359",
			"title": "Aeronautics - Airport Features",
			"category": "Transportation"
		},
		{
			"id": "i5R",
			"wrrID": "DE_Multimodal_9579",
			"title": "Aeronautics - Runway Centerlines",
			"category": "Transportation"
		},
		{
			"id": "XC8",
			"wrrID": "Permitting_and_Monitoring_4420",
			"title": "SIRS Projects",
			"category": "Impaired Areas"
		},
		{
			"id": "aOo",
			"wrrID": "DE_DNREC_DEN_Features_6778",
			"title": "Solid and Hazardous Waste",
			"category": "Impaired Areas"
		},
		{
			"id": "Hzb",
			"wrrID": "DE_DNREC_DEN_Features_7481",
			"title": "Spray Irrigation",
			"category": "Impaired Areas"
		},
		{
			"id": "wYP",
			"wrrID": "DE_DNREC_DEN_Features_6802",
			"title": "Certified Brownfields",
			"category": "Impaired Areas"
		},
		{
			"id": "DXF",
			"wrrID": "DE_DNREC_DEN_Features_8717",
			"title": "Leaking Underground Storage Tanks",
			"category": "Impaired Areas"
		},
		{
			"id": "VP6",
			"wrrID": "WRR_DE_ATTAINS_2897",
			"title": "ATTAINS - Assessment Lines",
			"category": "ATTAINS"
		},
		{
			"id": "WSg",
			"wrrID": "WRR_DE_ATTAINS_5925",
			"title": "ATTAINS - Assessment Areas",
			"category": "ATTAINS"
		},
		{
			"id": "of0",
			"wrrID": "WRR_DE_ATTAINS_815",
			"title": "ATTAINS - Assessment Unit Catchment Associations",
			"category": "ATTAINS"
		},
		{
			"id": "VUq",
			"wrrID": "NPDES_NP21_1987",
			"title": "NPDES Point Source Outfalls",
			"category": "NPDES"
		},
		{
			"id": "3gP",
			"wrrID": "MS4_Phase_I_Boundaries_4229",
			"title": "MS4 Permitted Areas (Phase 1)",
			"category": "NPDES"
		},
		{
			"id": "nxi",
			"wrrID": "MS4_Phase_II_Boundaries_518",
			"title": "MS4 Permitted Areas (Phase 2)",
			"category": "NPDES"
		},
		{
			"id": "YHG",
			"wrrID": "USA_States_Generalized_8861",
			"title": "State Boundary",
			"category": "Boundary"
		},
		{
			"id": "JhI",
			"wrrID": "DE_Boundaries_3135",
			"title": "County Boundaries",
			"category": "Boundary"
		},
		{
			"id": "J0G",
			"wrrID": "DE_StateParcels_8593",
			"title": "Public State Tax Parcels",
			"category": "Boundary"
		},
		{
			"id": "J7p",
			"wrrID": "DE_Boundaries_2732",
			"title": "Community Boundaries",
			"category": "Boundary"
		},
		{
			"id": "A3b",
			"wrrID": "NaturalGas_InterIntrastate_Pipelines_US_EIA_7371",
			"title": "Natural Gas Interstate and Intrastate Pipelines",
			"category": "Misc. (can be moved later)"
		}
	]
}